iman_set_selenium_utils/__init__.py
iman_set_selenium_utils/adfs_login.py
iman_set_selenium_utils/iman_set_selenium_utils.py
wr_test/__init__.py
wr_test/adfs_login.py
wr_test/main.py
wr_test/wr_test.py
wr_test-101.1337.dist-info/LICENSE.txt
wr_test-101.1337.dist-info/METADATA
wr_test-101.1337.dist-info/WHEEL
wr_test-101.1337.dist-info/top_level.txt
wr_test-101.1337.dist-info/RECORD
